foliant/preprocessors/templateparser/__init__.py
foliant/preprocessors/templateparser/templateparser.py
foliant/preprocessors/templateparser/engines/__init__.py
foliant/preprocessors/templateparser/engines/base.py
foliant/preprocessors/templateparser/engines/jinja2.py
foliantcontrib.templateparser-1.0.6.dist-info/LICENSE
foliantcontrib.templateparser-1.0.6.dist-info/METADATA
foliantcontrib.templateparser-1.0.6.dist-info/WHEEL
foliantcontrib.templateparser-1.0.6.dist-info/top_level.txt
foliantcontrib.templateparser-1.0.6.dist-info/RECORD
